{
  "schema_version": "2.0-simple",
  "year": 2010,
  "title": "European Youth Orienteering Championships 2010",
  "city": "Soria",
  "country": "Spain",
  "date": "July 1-4",
  "start_date": "2010-07-01",
  "end_date": "2010-07-04",
  "long": {
    "place": "La Cruz de Piedra",
    "map_name": "La Cruz de Piedra",
    "categories": {
      "M16": {
        "place": "La Cruz de Piedra",
        "map_name": "La Cruz de Piedra",
        "distance_km": 6.7,
        "elevation_m": 280,
        "control_points": 16,
        "field_size": 82
      },
      "M18": {
        "place": "La Cruz de Piedra",
        "map_name": "La Cruz de Piedra",
        "distance_km": 7.7,
        "elevation_m": 320,
        "control_points": 19,
        "field_size": 95
      },
      "W16": {
        "place": "La Cruz de Piedra",
        "map_name": "La Cruz de Piedra",
        "distance_km": 4.7,
        "elevation_m": 200,
        "control_points": 12,
        "field_size": 75
      },
      "W18": {
        "place": "La Cruz de Piedra",
        "map_name": "La Cruz de Piedra",
        "distance_km": 5.5,
        "elevation_m": 230,
        "control_points": 16,
        "field_size": 71
      }
    }
  },
  "sprint": {
    "place": "Soria",
    "map_name": "Soria",
    "categories": {
      "M16": {
        "place": "Soria",
        "map_name": "Soria",
        "distance_km": 2.7,
        "elevation_m": 20,
        "control_points": 16,
        "field_size": 83
      },
      "M18": {
        "place": "Soria",
        "map_name": "Soria",
        "distance_km": 2.9,
        "elevation_m": 25,
        "control_points": 16,
        "field_size": 95
      },
      "W16": {
        "place": "Soria",
        "map_name": "Soria",
        "distance_km": 2.2,
        "elevation_m": 20,
        "control_points": 15,
        "field_size": 76
      },
      "W18": {
        "place": "Soria",
        "map_name": "Soria",
        "distance_km": 2.6,
        "elevation_m": 15,
        "control_points": 13,
        "field_size": 73
      }
    }
  },
  "relay": {
    "place": "Valonsandero-Oeste",
    "map_name": "Valonsandero-Oeste",
    "categories": {
      "M16": {
        "place": null,
        "map_name": null,
        "distance_km": null,
        "elevation_m": null,
        "control_points": null,
        "field_size": 22
      },
      "M18": {
        "place": null,
        "map_name": null,
        "distance_km": null,
        "elevation_m": null,
        "control_points": null,
        "field_size": 29
      },
      "W16": {
        "place": "Valonsandero-Oeste",
        "map_name": "Valonsandero-Oeste",
        "distance_km": 4.0,
        "elevation_m": 125,
        "control_points": 17,
        "field_size": 19
      },
      "W18": {
        "place": "Valonsandero-Oeste",
        "map_name": "Valonsandero-Oeste",
        "distance_km": 4.6,
        "elevation_m": 140,
        "control_points": 17,
        "field_size": 22
      }
    }
  }
}
